diagtest/__init__.py
diagtest/__main__.py
diagtest/assertion.py
diagtest/compiler.py
diagtest/default.py
diagtest/dialect.py
diagtest/driver.py
diagtest/exceptions.py
diagtest/language.py
diagtest/log.py
diagtest/printer.py
diagtest/py.typed
diagtest/report.py
diagtest/test.py
diagtest/util.py
diagtest/compilers/__init__.py
diagtest/compilers/clang.py
diagtest/compilers/gcc.py
diagtest/compilers/msvc.py
diagtest/languages/__init__.py
diagtest/languages/cfamily.py
diagtest/output/__init__.py
diagtest/output/json.py
diagtest/output/junit.py
diagtest/output/terminal.py
diagtest-0.1.2.dist-info/LICENSE
diagtest-0.1.2.dist-info/METADATA
diagtest-0.1.2.dist-info/WHEEL
diagtest-0.1.2.dist-info/entry_points.txt
diagtest-0.1.2.dist-info/top_level.txt
diagtest-0.1.2.dist-info/RECORD
